{
  "has_narrative": true,
  "reviews_analyzed": 5,
  "review_count_ta": null,
  "ta_rating": null,
  "praise_themes": [
    {
      "aspect": "service",
      "label": "Service & Hospitality",
      "mentions": 6,
      "quotes": [
        "We had a wonderful Sunday roast at The Fox in Loxley. We arrived just after 12 and were seated at a table by the fireplace.",
        "Wow! This place is a rare gem!\nFrom the cosy atmosphere, with locals and tourists alike, to the kind and welcoming staff who are attentive to your nee"
      ]
    },
    {
      "aspect": "food_quality",
      "label": "Food Quality",
      "mentions": 2,
      "quotes": [
        "Not local to the area, we had asked for recommendations for dining and The Fox lived delightfully up to them."
      ]
    },
    {
      "aspect": "ambience",
      "label": "Atmosphere & Setting",
      "mentions": 2,
      "quotes": []
    },
    {
      "aspect": "speed",
      "label": "Speed & Efficiency",
      "mentions": 1,
      "quotes": []
    },
    {
      "aspect": "value",
      "label": "Value for Money",
      "mentions": 1,
      "quotes": []
    }
  ],
  "criticism_themes": [],
  "strongest_positive_quotes": [
    "We had a wonderful Sunday roast at The Fox in Loxley. We arrived just after 12 and were seated at a table by the fireplace.",
    "Not local to the area, we had asked for recommendations for dining and The Fox lived delightfully up to them.",
    "Wow! This place is a rare gem!\nFrom the cosy atmosphere, with locals and tourists alike, to the kind and welcoming staff who are attentive to your nee"
  ],
  "strongest_constructive_quotes": [],
  "aspect_scores": {
    "service": {
      "positive": 6,
      "negative": 0,
      "sentiment": 10.0
    },
    "speed": {
      "positive": 1,
      "negative": 0,
      "sentiment": 10.0
    },
    "food_quality": {
      "positive": 2,
      "negative": 0,
      "sentiment": 10.0
    },
    "ambience": {
      "positive": 2,
      "negative": 0,
      "sentiment": 10.0
    },
    "value": {
      "positive": 1,
      "negative": 0,
      "sentiment": 10.0
    }
  },
  "has_dated_reviews": false,
  "date_range": null,
  "recent_window": null,
  "analysis": {
    "reviews_analyzed": 5,
    "aspect_scores": {
      "service": {
        "score": 10.0,
        "positive": 4,
        "negative": 0,
        "mentions": 4
      },
      "speed": {
        "score": 10.0,
        "positive": 1,
        "negative": 0,
        "mentions": 1
      },
      "food_quality": {
        "score": 10.0,
        "positive": 2,
        "negative": 0,
        "mentions": 2
      },
      "ambience": {
        "score": 10.0,
        "positive": 2,
        "negative": 0,
        "mentions": 2
      },
      "value": {
        "score": 10.0,
        "positive": 1,
        "negative": 0,
        "mentions": 1
      }
    },
    "praise_themes": [
      {
        "aspect": "service",
        "label": "Service & Hospitality",
        "mentions": 4,
        "quotes": [
          "The service was incredible, James, our waiter was friendly, chatty and very efficient",
          "From the cosy atmosphere, with locals and tourists alike, to the kind and welcoming staff who are attentive to your needs"
        ]
      },
      {
        "aspect": "food_quality",
        "label": "Food Quality",
        "mentions": 2,
        "quotes": [
          "Do excuse the bite out of the cheesecake/lemon meringue photo - it was that delicious, we couldn’t wait",
          "...tarter through to desert was absolutely delicious"
        ]
      },
      {
        "aspect": "ambience",
        "label": "Atmosphere & Setting",
        "mentions": 2,
        "quotes": [
          "Beautifully decorated with a charming modern food menu"
        ]
      },
      {
        "aspect": "speed",
        "label": "Speed & Efficiency",
        "mentions": 1,
        "quotes": []
      },
      {
        "aspect": "value",
        "label": "Value for Money",
        "mentions": 1,
        "quotes": [
          "Reasonable amount of parking space"
        ]
      }
    ],
    "criticism_themes": [],
    "rating_distribution": {
      "5": 5
    },
    "average_sample_rating": 5.0,
    "sentiment_distribution": {
      "positive": 5
    },
    "risk_flags": [],
    "trajectory": "stable",
    "trajectory_method": "positional",
    "per_review": [
      {
        "rating": 5,
        "sentiment": "positive",
        "snippet": "The service was incredible, James, our waiter was friendly, chatty and very efficient",
        "full_text": "We had a wonderful Sunday roast at The Fox in Loxley. We arrived just after 12 and were seated at a table by the fireplace. The service was incredible, James, our waiter was friendly, chatty and very efficient. The food was great and it was nice to be able to see the chef serving up the meals at the pass and the smooth transition from the pass to the tables. The atmosphere was bubbly and light and the pub was full by 13.30. Would definitely recommend booking before you go to guarantee a table. We hadn't booked but the staff were incredibly kind and squeezed us in and we are really happy they did! It was honestly one of the best Sunday roasts we had eaten out and really reasonably priced as well. There were the options to have a small or large portion and even the small had plenty on it (I was enjoying it so much I forgot to take a photo.)\n\nSet in the middle of the village you can tell that the pub is popular and the heart of the local community. Would definitely visit again!",
        "aspects": [
          "service",
          "speed"
        ],
        "risk_count": 0,
        "date": null,
        "source": null
      },
      {
        "rating": 5,
        "sentiment": "positive",
        "snippet": "Beautifully decorated with a charming modern food menu",
        "full_text": "Not local to the area, we had asked for recommendations for dining and The Fox lived delightfully up to them. You can feel the love from the community which flows in to the pub. Beautifully decorated with a charming modern food menu. Do excuse the bite out of the cheesecake/lemon meringue photo - it was that delicious, we couldn’t wait! Belinda and Adrian deserve all the success here, with the merge of Belinda’s homely hospitality and Adrian’s flair for elevated pub cuisine - you’re lucky if this is your local. Keep supporting it!",
        "aspects": [
          "food_quality",
          "ambience"
        ],
        "risk_count": 0,
        "date": null,
        "source": null
      },
      {
        "rating": 5,
        "sentiment": "positive",
        "snippet": "From the cosy atmosphere, with locals and tourists alike, to the kind and welcoming staff who are attentive to your needs",
        "full_text": "Wow! This place is a rare gem!\nFrom the cosy atmosphere, with locals and tourists alike, to the kind and welcoming staff who are attentive to your needs. In love with the food, hearty fare full of love and care. Portion sizes are generous. So many gluten free options all home made. The pie has a reputation, and doesn't disappoint. Will come back again and can't recommend enough. Thank you chef Gemma and Andy and Sally for a joyful and fulfilling evening.",
        "aspects": [
          "service",
          "ambience"
        ],
        "risk_count": 0,
        "date": null,
        "source": null
      },
      {
        "rating": 5,
        "sentiment": "positive",
        "snippet": "Really enjoyed our bank holiday lunch here Portion sizes were so generous we had to take some home but that in no way affected the quality, everything from starter through to desert was absolutely del",
        "full_text": "Really enjoyed our bank holiday lunch here Portion sizes were so generous we had to take some home but that in no way affected the quality, everything from starter through to desert was absolutely delicious! Staff were attentive and friendly throughout, and there are a couple of cracking pints on draught. I wouldn't hesitate to recommend this great pub to anyone in the area.",
        "aspects": [
          "food_quality",
          "service"
        ],
        "risk_count": 0,
        "date": null,
        "source": null
      },
      {
        "rating": 5,
        "sentiment": "positive",
        "snippet": "Reasonable amount of parking space",
        "full_text": "Reasonable amount of parking space. Great welcome and very friendly staff. Good British pub atmosphere. Varied tables and seating either in the main area or quieter off to one side. Good selection of dishes and drinks. Super local food well prepared and presented. Sensible prices and no pressure. A really great place and I hope you enjoy your visit as much as I did.",
        "aspects": [
          "service",
          "value"
        ],
        "risk_count": 0,
        "date": null,
        "source": null
      }
    ]
  },
  "volume_signals": {
    "volume_tier": "adequate",
    "volume_note": "271 reviews — adequate but not dominant. 5 consecutive low ratings could drop average by ~0.1.",
    "rating_position": "premium",
    "rating_note": "4.6/5 places you in the top tier of Google search results. This drives discovery.",
    "aggregate_rating": 4.6,
    "review_count": 271
  }
}