{
  "venue": "Arrow Mill",
  "month": "2026-04",
  "scorecard": {
    "experience": 9.42,
    "visibility": 8.5,
    "trust": 9.73,
    "conversion": 5.5,
    "prestige": 1.5,
    "overall": 7.93
  },
  "deltas": null,
  "priority_actions": [
    {
      "title": "Fix the digital shopfront — you're losing walk-ins",
      "status": "ongoing",
      "priority": 7.0,
      "dimension": "conversion"
    },
    {
      "title": "Lean into service & hospitality — it's what guests are buying",
      "status": "new",
      "priority": 7.0,
      "dimension": "experience"
    },
    {
      "title": "Protect the 4.5/5 rating — it took years to build",
      "status": "new",
      "priority": 7.0,
      "dimension": "visibility"
    }
  ],
  "watch_items": [
    {
      "title": "Solid score rests on thin evidence — more data could shift it",
      "status": "new"
    },
    {
      "title": "Monitor local competitor openings and closures",
      "status": "new"
    }
  ],
  "active_recommendations": 6
}